pendragondi_api_raw/__init__.py
pendragondi_api_raw/analyzer.py
pendragondi_api_raw/cli.py
pendragondi_api_raw/config.py
pendragondi_api_raw/constants.py
pendragondi_api_raw/decorator.py
pendragondi_api_raw/decorator_async.py
pendragondi_api_raw/logger.py
pendragondi_api_raw/report.py
pendragondi_api_raw/utils.py
pendragondi_api_raw-1.0.0.dist-info/licenses/LICENSE
pendragondi_api_raw-1.0.0.dist-info/METADATA
pendragondi_api_raw-1.0.0.dist-info/WHEEL
pendragondi_api_raw-1.0.0.dist-info/entry_points.txt
pendragondi_api_raw-1.0.0.dist-info/top_level.txt
pendragondi_api_raw-1.0.0.dist-info/RECORD
