Metadata-Version: 2.4
Name: pendragondi-api-raw
Version: 1.0.0
Summary: PendragonDI API – lightweight tool to detect redundant API call waste, inefficiency, and missed savings in Python apps.
Author-email: jinpendragon <pendragondi@pendragondi.dev>
License: MIT License
Project-URL: Homepage, https://github.com/PendragonDI/pendragondi-api-raw
Project-URL: Repository, https://github.com/PendragonDI/pendragondi-api-raw
Project-URL: Documentation, https://github.com/PendragonDI/pendragondi-api-raw
Project-URL: Bug Tracker, https://github.com/PendragonDI/pendragondi-api-raw/issues
Project-URL: Changelog, https://github.com/PendragonDI/pendragondi-api-raw/releases
Requires-Python: >=3.9
License-File: LICENSE
Requires-Dist: typer>=0.9.0
Requires-Dist: rich>=13.0.0
Requires-Dist: pydantic>=2.0.0
Requires-Dist: sqlite-utils>=3.0.0
Requires-Dist: pyyaml>=6.0
Dynamic: license-file
